{
  "asOfDate": "2026-06-05",
  "source": "Yahoo Finance",
  "updatedAt": "2026-06-05T23:09:18.373828+00:00",
  "prices": {
    "VOO": {
      "price": 678.0,
      "change": -18.06,
      "changePercent": -2.59
    },
    "QQQ": {
      "price": 705.06,
      "change": -35.55,
      "changePercent": -4.8
    },
    "SCHD": {
      "price": 32.3,
      "change": -0.29,
      "changePercent": -0.89
    },
    "VTI": {
      "price": 363.38,
      "change": -10.0,
      "changePercent": -2.68
    },
    "SPY": {
      "price": 737.55,
      "change": -19.54,
      "changePercent": -2.58
    },
    "AAPL": {
      "price": 307.34,
      "change": -3.89,
      "changePercent": -1.25
    },
    "MSFT": {
      "price": 416.67,
      "change": -11.38,
      "changePercent": -2.66
    },
    "GOOGL": {
      "price": 368.53,
      "change": -3.66,
      "changePercent": -0.98
    },
    "AMZN": {
      "price": 246.03,
      "change": -7.76,
      "changePercent": -3.06
    },
    "NVDA": {
      "price": 205.1,
      "change": -13.56,
      "changePercent": -6.2
    },
    "TSLA": {
      "price": 391.0,
      "change": -27.45,
      "changePercent": -6.56
    }
  }
}