{
  "asOfDate": "2026-01-30",
  "source": "Yahoo Finance",
  "updatedAt": "2026-01-30T22:26:27.651662+00:00",
  "prices": {
    "VOO": {
      "price": 636.22,
      "change": -2.05,
      "changePercent": -0.32
    },
    "QQQ": {
      "price": 621.87,
      "change": -7.56,
      "changePercent": -1.2
    },
    "SCHD": {
      "price": 29.82,
      "change": 0.45,
      "changePercent": 1.53
    },
    "VTI": {
      "price": 340.57,
      "change": -1.72,
      "changePercent": -0.5
    },
    "SPY": {
      "price": 691.97,
      "change": -2.07,
      "changePercent": -0.3
    },
    "AAPL": {
      "price": 259.48,
      "change": 1.2,
      "changePercent": 0.46
    },
    "MSFT": {
      "price": 430.29,
      "change": -3.21,
      "changePercent": -0.74
    },
    "GOOGL": {
      "price": 338.0,
      "change": -0.25,
      "changePercent": -0.07
    },
    "AMZN": {
      "price": 239.3,
      "change": -2.43,
      "changePercent": -1.01
    },
    "NVDA": {
      "price": 191.13,
      "change": -1.38,
      "changePercent": -0.72
    },
    "TSLA": {
      "price": 430.41,
      "change": 13.85,
      "changePercent": 3.32
    }
  }
}