{
  "asOfDate": "2026-04-22",
  "source": "Yahoo Finance",
  "updatedAt": "2026-04-22T22:48:35.671555+00:00",
  "prices": {
    "VOO": {
      "price": 653.9,
      "change": 6.65,
      "changePercent": 1.03
    },
    "QQQ": {
      "price": 655.11,
      "change": 10.78,
      "changePercent": 1.67
    },
    "SCHD": {
      "price": 31.01,
      "change": 0.03,
      "changePercent": 0.1
    },
    "VTI": {
      "price": 351.22,
      "change": 3.38,
      "changePercent": 0.97
    },
    "SPY": {
      "price": 711.21,
      "change": 7.13,
      "changePercent": 1.01
    },
    "AAPL": {
      "price": 273.17,
      "change": 7.0,
      "changePercent": 2.63
    },
    "MSFT": {
      "price": 432.92,
      "change": 8.76,
      "changePercent": 2.07
    },
    "GOOGL": {
      "price": 339.32,
      "change": 7.03,
      "changePercent": 2.12
    },
    "AMZN": {
      "price": 255.36,
      "change": 5.45,
      "changePercent": 2.18
    },
    "NVDA": {
      "price": 202.5,
      "change": 2.62,
      "changePercent": 1.31
    },
    "TSLA": {
      "price": 387.51,
      "change": 1.09,
      "changePercent": 0.28
    }
  }
}