{
  "asOfDate": "2026-04-16",
  "source": "Yahoo Finance",
  "updatedAt": "2026-04-16T22:40:18.429601+00:00",
  "prices": {
    "VOO": {
      "price": 644.86,
      "change": 1.41,
      "changePercent": 0.22
    },
    "QQQ": {
      "price": 640.47,
      "change": 3.07,
      "changePercent": 0.48
    },
    "SCHD": {
      "price": 30.81,
      "change": 0.16,
      "changePercent": 0.52
    },
    "VTI": {
      "price": 346.03,
      "change": 0.79,
      "changePercent": 0.23
    },
    "SPY": {
      "price": 701.66,
      "change": 1.72,
      "changePercent": 0.25
    },
    "AAPL": {
      "price": 263.4,
      "change": -3.03,
      "changePercent": -1.14
    },
    "MSFT": {
      "price": 420.26,
      "change": 9.04,
      "changePercent": 2.2
    },
    "GOOGL": {
      "price": 336.02,
      "change": -1.1,
      "changePercent": -0.33
    },
    "AMZN": {
      "price": 249.7,
      "change": 1.2,
      "changePercent": 0.48
    },
    "NVDA": {
      "price": 198.35,
      "change": -0.52,
      "changePercent": -0.26
    },
    "TSLA": {
      "price": 388.9,
      "change": -3.05,
      "changePercent": -0.78
    }
  }
}