{
  "asOfDate": "2026-02-05",
  "source": "Yahoo Finance",
  "updatedAt": "2026-02-05T22:28:42.229313+00:00",
  "prices": {
    "VOO": {
      "price": 623.1,
      "change": -7.81,
      "changePercent": -1.24
    },
    "QQQ": {
      "price": 597.03,
      "change": -8.72,
      "changePercent": -1.44
    },
    "SCHD": {
      "price": 30.97,
      "change": -0.04,
      "changePercent": -0.13
    },
    "VTI": {
      "price": 333.9,
      "change": -4.35,
      "changePercent": -1.29
    },
    "SPY": {
      "price": 677.62,
      "change": -8.57,
      "changePercent": -1.25
    },
    "AAPL": {
      "price": 275.91,
      "change": -0.58,
      "changePercent": -0.21
    },
    "MSFT": {
      "price": 393.67,
      "change": -20.52,
      "changePercent": -4.95
    },
    "GOOGL": {
      "price": 331.25,
      "change": -1.79,
      "changePercent": -0.54
    },
    "AMZN": {
      "price": 222.69,
      "change": -10.3,
      "changePercent": -4.42
    },
    "NVDA": {
      "price": 171.88,
      "change": -2.31,
      "changePercent": -1.33
    },
    "TSLA": {
      "price": 397.21,
      "change": -8.8,
      "changePercent": -2.17
    }
  }
}